torch_formatter/__init__.py
torch_formatter/_utils.py
torch_formatter-0.0.3.dist-info/LICENCE
torch_formatter-0.0.3.dist-info/METADATA
torch_formatter-0.0.3.dist-info/WHEEL
torch_formatter-0.0.3.dist-info/top_level.txt
torch_formatter-0.0.3.dist-info/zip-safe
torch_formatter-0.0.3.dist-info/RECORD
