Metadata-Version: 2.1
Name: torch-formatter
Version: 0.0.3
Summary: Fancy PyTorch education output for Jupyter
Home-page: https://github.com/andrewsonin/torch_formatter
Author: Andrew Sonin
Author-email: sonin.cel@gmail.com
License: MIT License
Platform: UNKNOWN
Classifier: Programming Language :: Python :: 3
Classifier: Topic :: Software Development :: Libraries
Classifier: Operating System :: OS Independent
Classifier: Typing :: Typed
Classifier: Development Status :: 2 - Pre-Alpha
Classifier: License :: OSI Approved :: MIT License
Requires-Python: ~=3.8
